regex_build
