Metadata-Version: 2.1
Name: regex-build
Version: 1.0.1
Summary: Build complex one-line regex strings.
Home-page: https://github.com/huntfx/regex-build
Author: Peter Hunt
Author-email: peter@huntfx.uk
License: MIT
Download-URL: https://github.com/huntfx/regex-build/archive/1.0.1.tar.gz
Project-URL: Documentation, https://github.com/huntfx/regex-build/wiki
Project-URL: Source, https://github.com/huntfx/regex-build
Project-URL: Issues, https://github.com/huntfx/regex-build/issues
Keywords: regex,build,generate,re,auto,create
Platform: UNKNOWN
Classifier: Development Status :: 4 - Beta
Classifier: Intended Audience :: Developers
Classifier: License :: OSI Approved :: MIT License
Classifier: Operating System :: Microsoft :: Windows
Classifier: Operating System :: POSIX :: Linux
Classifier: Programming Language :: Python
Classifier: Programming Language :: Python :: 2
Classifier: Programming Language :: Python :: 2.7
Classifier: Programming Language :: Python :: 3.4
Classifier: Programming Language :: Python :: 3.5
Classifier: Programming Language :: Python :: 3.6
Classifier: Programming Language :: Python :: 3.7
Classifier: Programming Language :: Python :: 3.8
Classifier: Programming Language :: Python :: 3.9
Requires-Python: >=2.7
